rtcqs/__init__.py
rtcqs/resources.py
rtcqs/rtcqs.py
rtcqs/rtcqs_gui.py
rtcqs/rtcqs_qt_gui.py
rtcqs-0.6.7.dist-info/licenses/LICENSE
rtcqs-0.6.7.dist-info/METADATA
rtcqs-0.6.7.dist-info/WHEEL
rtcqs-0.6.7.dist-info/entry_points.txt
rtcqs-0.6.7.dist-info/top_level.txt
rtcqs-0.6.7.dist-info/RECORD
