Metadata-Version: 2.4
Name: rtcqs
Version: 0.6.7
Summary: Linux audio performance analyzer
Author-email: Jeremy Jongepier <jeremy@autostatic.com>
License-Expression: MIT
Project-URL: Homepage, https://codeberg.org/rtcqs/rtcqs
Keywords: real-time,priorities,audio,limits
Classifier: Programming Language :: Python
Classifier: Programming Language :: Python :: 3
Classifier: Operating System :: POSIX :: Linux
Classifier: Topic :: Utilities
Classifier: Topic :: System :: Installation/Setup
Requires-Python: >=3.6
License-File: LICENSE
Requires-Dist: FreeSimpleGUI
Dynamic: license-file
